
[
  {
    "name": "Limgrave",
    "total": 22,
    "defeated": 22,
    "bosses": [
"Beastman of Farum Azula",
"Bell Bearing Hunter",
"Black Knife Assassin",
"Bloodhound Knight Darriwil",
"Crucible Knight",
"Deathbird",
"Demi-Human Chief",
"Erdtree Burial Watchdog (Stormfoot Catacombs)",
"Flying Dragon Agheel",
"Godrick the Grafted",
"Grafted Scion",
"Grave Warden Duelist",
"Guardian Golem",
"Mad Pumpkin Head",
"Margit, the Fell Omen",
"Night's Cavalry",
"Patches",
"Soldier of God, Rick",
"Stonedigger Troll",
"Tibia Mariner",
"Tree Sentinel",
"Ulcerated Tree Spirit"],
    "defeated_bosses": [true, true, true, true, true, true, true, true, true, true, true, true, true, true, true, true, true, true, true, true, true, true]
  },
  {
    "name": "Weeping Peninsula",
    "total": 10,
    "defeated": 10,
    "bosses": [
"Ancient Hero of Zamor",
"Cemetery Shade",
"Deathbird",
"Erdtree Avatar",
"Erdtree Burial Watchdog (Impaler's Catacombs)",
"Leonine Misbegotten",
"Miranda the Blighted Bloom",
"Night's Cavalry",
"Runebear",
"Scaly Misbegotten"],
    "defeated_bosses": [true, true, true, true, true, true, true, true, true, true]
  },
    {
    "name": "Liurnia of the Lakes",
    "total": 28,
    "defeated": 28,
    "bosses": [
"Adan, Thief of Fire",
"Alecto, Black Knife Ringleader",
"Bell Bearing Hunter",
"Black Knife Assassin",
"Bloodhound Knight",
"Bols, Carian Knight",
"Cemetery Shade",
"Cleanrot Knight",
"Crystalian",
"Crystalian Spear & Crystalian Staff (Duo)",
"Death Rite Bird",
"Deathbird",
"Erdtree Avatar (Liurnia Northeast)",
"Erdtree Avatar (Liurnia Southwest)",
"Erdtree Burial Watchdog",
"Glintstone Dragon Adula",
"Glintstone Dragon Smarag",
"Magma Wyrm Makar",
"Night's Cavalry (Liurnia North)",
"Night's Cavalry (Liurnia South)",
"Omenkiller",
"Onyx Lord",
"Red Wolf of Radagon",
"Rennala, Queen of the Full Moon",
"Royal Knight Loretta",
"Royal Revenant",
"Spirit-Caller Snail",
"Tibia Mariner"],
    "defeated_bosses": [true, true, true, true, true, true, true, true, true, true, true, true, true, true, true, true, true, true, true, true, true, true, true, true, true, true, true, true]
  },
    {
    "name": "Caelid",
    "total": 14,
    "defeated": 13,
    "bosses": [
"Cemetery Shade",
"Commander O'Neil",
"Crucible Knight and Misbegotten Warrior",
"Death Rite Bird",
"Decaying Ekzykes",
"Erdtree Burial Watchdog (Duo)",
"Fallingstar Beast",
"Frenzied Duelist",
"Mad Pumpkin Heads",
"Magma Wyrm",
"Night's Cavalry (Caelid)",
"Nox Swordstress & Nox Priest",
"Putrid Avatar",
"Starscourge Radahn"],
    "defeated_bosses": [true, true, true, true, true, true, true, true, false, true, true, true, true, true]
  },
  {
    "name": "Dragonbarrow",
    "total": 11,
    "defeated": 10,
    "bosses": [
"Battlemage Hugues",
"Beastman of Farum Azula (Duo)",
"Bell Bearing Hunter",
"Black Blade Kindred ",
"Cleanrot Knight (Duo)",
"Flying Dragon Greyll",
"Godskin Apostle",
"Night's Cavalry (Dragonbarrow)",
"Putrid Avatar",
"Putrid Crystalian Trio",
"Putrid Tree Spirit"],
    "defeated_bosses": [true, true, true, true, true, true, true, true, true, false, true]
  },
    {
    "name": "Altus Plateau",
    "total": 20,
    "defeated": 16,
    "bosses": [
"Ancient Dragon Lansseax",
"Ancient Hero of Zamor",
"Black Knife Assassin (Sage's Cave)",
"Black Knife Assassin (Sainted Hero's Grave)",
"Crystalian Spear & Crystalian Ringblade",
"Demi-Human Queen Gilika",
"Elemer of the Briar",
"Erdtree Burial Watchdog",
"Fallingstar Beast",
"Godefroy The Grafted",
"Godskin Apostle",
"Necromancer Garris",
"Night's Cavalry",
"Omenkiller & Miranda the Blighted Bloom",
"Perfumer Tricia and Misbegotten Warrior",
"Sanguine Noble",
"Stonedigger Troll",
"Tibia Mariner",
"Tree Sentinel (Duo)",
"Wormface"],
    "defeated_bosses": [true, true, true, true, true, true, true, true, true, true, true, true, false, false, true, false, false, true, true, true]
  },
    {
    "name": "Mt. Gelmir",
    "total": 10,
    "defeated": 9,
    "bosses": [
"Abductor Virgins (Duo)",
"Demi-Human Queen Maggie",
"Demi-Human Queen Margot",
"Full-Grown Fallingstar Beast",
"God-Devouring Serpent / Rykard, Lord of Blasphemy",
"Godskin Noble",
"Kindred of Rot (Duo)",
"Magma Wyrm (Fort Laiedd)",
"Red Wolf of the Champion",
"Ulcerated Tree Spirit"],
    "defeated_bosses": [true, true, true, true, true, true, true, true, true, false]
  },
   {
    "name": "Capital Outskirts",
    "total": 7,
    "defeated": 6,
    "bosses": [
"Bell Bearing Hunter",
"Crucible Knight & Crucible Knight Ordovis",
"Deathbird",
"Draconic Tree Sentinel",
"Fell Twins",
"Grave Warden Duelist",
"Onyx Lord"],
    "defeated_bosses": [true, true, true, true, true, false, true]
   },
    {
    "name": "Leyndell, Royal Capital",
    "total": 4,
    "defeated": 4,
    "bosses": [
"Esgar, Priest of Blood",
"Godfrey, First Elden Lord",
"Mohg, the Omen",
"Morgott, the Omen King"],
    "defeated_bosses": [true, true, true, true]
  },
    {
    "name": "Mountaintops of the Giants",
    "total": 9,
    "defeated": 6,
    "bosses": [
"Ancient Hero of Zamor",
"Borealis the Freezing Fog",
"Commander Niall",
"Death Rite Bird",
"Erdtree Avatar",
"Fire Giant",
"Godskin Apostle and Godskin Noble (Spiritcaller Snail)",
"Ulcerated Tree Spirit",
"Vyke, Knight of the Roundtable"],
    "defeated_bosses": [false, true, true, true, false, true, false, true, true]
  },
    {
    "name": "Crumbling Farum Azula",
    "total": 3,
    "defeated": 3,
    "bosses": [
"Godskin Duo",
"Beast Clergyman / Maliketh, the Black Blade",
"Dragonlord Placidusax"],
    "defeated_bosses": [true, true, true]
  },
    {
    "name": "Forbidden Lands",
    "total": 3,
    "defeated": 3,
    "bosses": [
"Black Blade Kindred",
"Night's Cavalry",
"Stray Mimic Tear"],
    "defeated_bosses": [true, true, true]
  },
    {
    "name": "Consecrated Snowfield",
    "total": 7,
    "defeated": 6,
    "bosses": [
"Astel, Stars of Darkness",
"Death Rite Bird",
"Great Wyrm Theodorix",
"Misbegotten Crusader",
"Night's Cavalry (Duo)",
"Putrid Avatar",
"Putrid Grave Warden Duelist"],
    "defeated_bosses": [true, true, true, true, true, true, false]
  },
    {
    "name": "Miquella's Haligtree",
    "total": 2,
    "defeated": 2,
    "bosses": [
"Loretta, Knight of the Haligtree",
"Malenia, Blade of Miquella (jebać cię ruda szmato)"],
    "defeated_bosses": [true, true]
  },
    {
    "name": "Siofra River",
    "total": 3,
    "defeated": 3,
    "bosses": [
"Ancestor Spirit",
"Dragonkin Soldier",
"Mohg, Lord of Blood"],
    "defeated_bosses": [true, true, true]
  },
    {
    "name": "Ainsel River",
    "total": 1,
    "defeated": 1,
    "bosses": [
"Dragonkin Soldier of Nokstella"],
    "defeated_bosses": [true]
  },
    {
    "name": "Nokron, Eternal City",
    "total": 3,
    "defeated": 3,
    "bosses": [
"Mimic Tear",
"Regal Ancestor Spirit",
"Valiant Gargoyle & Valiant Gargoyle (Twinblade)"],
    "defeated_bosses": [true, true, true]
  },
    {
    "name": "Deeproot Depths",
    "total": 3,
    "defeated": 3,
    "bosses": [
"Crucible Knight Siluria",
"Fia's Champions",
"Lichdragon Fortissax"],
    "defeated_bosses": [true, true, true]
  },
    {
    "name": "Lake of Rot",
    "total": 2,
    "defeated": 2,
    "bosses": [
"Astel, Naturalborn of the Void",
"Dragonkin Soldier"],
    "defeated_bosses": [true, true]
  },
    {
    "name": "Leyndell, Ashen Capital",
    "total": 4,
    "defeated": 4,
    "bosses": [
"Esgar, Priest of Blood",
"Godfrey, First Elden Lord (Hoarah Loux)",
"Mohg, the Omen",
"Sir Gideon Ofnir, the All-Knowing"],
    "defeated_bosses": [true, true, true, true]
  },
      {
    "name": "Elden Throne",
    "total": 1,
    "defeated": 1,
    "bosses": [
"Radagon of the Golden Order / Elden Beast"],
    "defeated_bosses": [true]
  },
  {
    "name": "Gravesite Plain",
    "total": 7,
    "defeated": 3,
    "bosses": [
"Blackgaol Knight",
"Chief Bloodfiend",
"Demi-Human Swordmaster Onze",
"Divine Beast Dancing Lion",
"Ghostflame Dragon",
"Rellana Twin Moon Knight",
"Red Bear"],
    "defeated_bosses": [true, false, false, true, true, false, false]
  },
  {
    "name": "Scadu Altus",
    "total": 14,
    "defeated": 6,
    "bosses": [
"Black Knight Edredd",
"Black Knight Garrew",
"Count Ymir, Mother of Fingers",
"Curseblade Labirith",
"Death Knight",
"Dryleaf Dane",
"Ghostflame Dragon",
"Golden Hippopotamus",
"Messmer the Impaler + Base Serpent Messmer",
"Metyr, Mother of Fingers",
"Rakshasa",
"Jori, Elder Inquisitor",
"Ralva the Great Red Bear",
"Tree Sentinel"],
    "defeated_bosses": [true, false, false, false, false, true, true, true, true, false, false, true, false, false]
  },
    {
    "name": "Rauh Base",
    "total": 2,
    "defeated": 0,
    "bosses": [
"Death Knight",
"Rugalea the Great Red Bear"],
    "defeated_bosses": [false, false]
  },
  {
    "name": "Cerulean Coast",
    "total": 4,
    "defeated": 2,
    "bosses": [
"Dancer of Ranah",
"Demi-Human Queen Marigga",
"Ghostflame Dragon",
"Putrescent Knight"],
    "defeated_bosses": [false, false, true, true]
  },
  {
    "name": "Charo's Hidden Grave",
    "total": 3,
    "defeated": 2,
    "bosses": [
"Death Rite Bird",
"Lamenter",
"Tibia Mariner"],
    "defeated_bosses": [true, true, false]
  },
  {
    "name": "Jagged Peak",
    "total": 4,
    "defeated": 3,
    "bosses": [
"Ancient Dragon-Man",
"Ancient Dragon Senessax",
"Bayle the Dread",
"Jagged Peak Drake x2"],
    "defeated_bosses": [true, false, true, true]
  },
  {
    "name": "Abyssal Woods",
    "total": 1,
    "defeated": 1,
    "bosses": [
"Midra Lord of Frenzied Flame"],
    "defeated_bosses": [true]
  },
  {
    "name": "Scaduview",
    "total": 4,
    "defeated": 2,
    "bosses": [
"Fallingstar Beast",
"Scadutree Avatar",
"Commander Gaius",
"Tree Sentinel"],
    "defeated_bosses": [false, true, false, true]
  },
  {
    "name": "Ancient Ruins of Rauh",
    "total": 2,
    "defeated": 2,
    "bosses": [
"Divine Beast Dancing Lion",
"❤️ Romina, Saint of the Bud ❤️"],
    "defeated_bosses": [true, true]
  },
  {
    "name": "Enir-Ilim",
    "total": 2,
    "defeated": 2,
    "bosses": [
"Leda and Allies",
"Promised Consort Radahn + Radahn Consort of Miquella (Dziękuję Maja za użyczenie kompa do tego skurwysyna ❤️)"],
    "defeated_bosses": [true, true]
  }
]
